src/__init__.py
src/db.sqlite3
src/djangor/__init__.py
src/djangor/asgi.py
src/djangor/settings.py
src/djangor/urls.py
src/djangor/wsgi.py
testdj_project-0.1.0.dist-info/METADATA
testdj_project-0.1.0.dist-info/WHEEL
testdj_project-0.1.0.dist-info/RECORD
